MANIFEST.in
README.md
setup.cfg
setup.py
stratus_api/document/__init__.py
stratus_api/document/base.py
stratus_api/document/create.py
stratus_api/document/get.py
stratus_api/document/update.py
stratus_api/document/utilities.py
stratus_api_document.egg-info/PKG-INFO
stratus_api_document.egg-info/SOURCES.txt
stratus_api_document.egg-info/dependency_links.txt
stratus_api_document.egg-info/requires.txt
stratus_api_document.egg-info/top_level.txt