Metadata-Version: 2.1
Name: stratus-api-document
Version: 0.0.5
Summary: An API stratus_api for simplified development
Home-page: https://bitbucket.org/adarainc/stratus-api-firestore
Author: DOT
Author-email: dot@adara.com
Classifier: Programming Language :: Python :: 3
Classifier: License :: OSI Approved :: MIT License
Classifier: Operating System :: OS Independent
Requires-Python: >=3.11
